ascon/__init__.py
ascon/ascon.py
ascon-0.0.2.dist-info/LICENSE
ascon-0.0.2.dist-info/METADATA
ascon-0.0.2.dist-info/WHEEL
ascon-0.0.2.dist-info/top_level.txt
ascon-0.0.2.dist-info/RECORD
