Metadata-Version: 2.1
Name: ascon
Version: 0.0.2
Summary: Lightweight authenticated encryption and hashing
Home-page: https://ascon.iaik.tugraz.at/
License: CC0 1.0
Platform: UNKNOWN
Classifier: Programming Language :: Python :: 3
Classifier: License :: CC0 1.0 Universal (CC0 1.0) Public Domain Dedication
Classifier: Operating System :: OS Independent
Requires-Python: >=3.8
License-File: LICENSE
